[{"__type__":"cc.SpriteFrame","content":{"name":"default_btn_disabled","texture":"71VhFCTINJM6/Ky3oX9nBT","rect":[0,0,40,40],"offset":[0,0],"originalSize":[40,40],"capInsets":[12,12,12,12]}},{"__type__":"cc.SpriteFrame","content":{"name":"返回游戏","texture":"4aIk+hPWpMU5ORG2arNYeA","rect":[52,28,447,224],"offset":[0,0.5],"originalSize":[551,281],"capInsets":[0,0,0,0]}},{"__type__":"cc.SpriteFrame","content":{"name":"海报（没有人物背景）","texture":"f7n5bXr6BMxJ++1I9RSife","rect":[0,0,750,1350],"offset":[0,0],"originalSize":[750,1350],"capInsets":[0,0,0,0]}},{"__type__":"cc.SpriteFrame","content":{"name":"default_btn_pressed","texture":"b4P/PCArtIdIH38t6mlw8Y","rect":[0,0,40,40],"offset":[0,0],"originalSize":[40,40],"capInsets":[12,12,12,12]}},{"__type__":"cc.SpriteFrame","content":{"name":"default_btn_normal","texture":"e8Ueib+qJEhL6mXAHdnwbi","rect":[0,0,40,40],"offset":[0,0],"originalSize":[40,40],"capInsets":[12,12,12,12]}},[{"__type__":"cc.SceneAsset","_name":"GetStorage","scene":{"__id__":1},"asyncLoadAssets":null},{"__type__":"cc.Scene","_name":"New Node","_children":[{"__id__":2}],"_anchorPoint":{"__type__":"cc.Vec2"},"_trs":{"__type__":"TypedArray","ctor":"Float64Array","array":[0,0,0,0,0,0,1,1,1,1]},"autoReleaseAssets":false},{"__type__":"cc.Node","_name":"Canvas","_parent":{"__id__":1},"_children":[{"__id__":3},{"__id__":4},{"__id__":5},{"__id__":30}],"_components":[{"__type__":"cc.Canvas","node":{"__id__":2},"_designResolution":{"__type__":"cc.Size","width":750,"height":1330},"_fitWidth":true},{"__type__":"cc.Widget","node":{"__id__":2},"_alignFlags":45,"_originalWidth":750,"_originalHeight":1330},{"__type__":"4fa03t+T1lLVp5PA0F8Bbhk","node":{"__id__":2},"bgm":{"__uuid__":"79vXmtsc1KyZuHyk7XpPbc"}},{"__type__":"d3968eK1upLwrIHz6kdz2gJ","node":{"__id__":2},"one":{"__id__":9},"two":{"__id__":13},"three":{"__id__":17},"four":{"__id__":21},"five":{"__id__":25},"six":{"__id__":29},"back":{"__id__":32},"one2":{"__id__":8},"two2":{"__id__":12},"three2":{"__id__":16},"four2":{"__id__":20},"five2":{"__id__":24},"six2":{"__id__":28}},{"__type__":"e6777CgYB1GdI7Kh2e5mnEV","node":{"__id__":2},"b1":{"__id__":9},"b2":{"__id__":13},"b3":{"__id__":17},"b4":{"__id__":21},"b5":{"__id__":25},"b6":{"__id__":29},"back":{"__id__":32},"yes":{"__uuid__":"25f+NufB1MNZ94yQQzf9wd"},"no":{"__uuid__":"2cUJjkA5VKe443T2q4KHEp"}}],"_contentSize":{"__type__":"cc.Size","width":750,"height":1330},"_trs":{"__type__":"TypedArray","ctor":"Float64Array","array":[375,665,0,0,0,0,1,1,1,1]},"_id":"a5esZu+45LA5mBpvttspPD"},{"__type__":"cc.Node","_name":"Main Camera","_parent":{"__id__":2},"_components":[{"__type__":"cc.Camera","node":{"__id__":3},"_clearFlags":7,"_depth":-1}],"_contentSize":{"__type__":"cc.Size","width":960,"height":640},"_trs":{"__type__":"TypedArray","ctor":"Float64Array","array":[0,0,224.30057958016963,0,0,0,1,1,1,1]}},{"__type__":"cc.Node","_name":"234结局成就_人物选择_进度条背景","_parent":{"__id__":2},"_components":[{"__type__":"cc.Sprite","node":{"__id__":4},"_materials":[{"__uuid__":"ecpdLyjvZBwrvm+cedCcQy"}],"_spriteFrame":{"__uuid__":"cbWifGtotPapKHPMu3px2J"}}],"_contentSize":{"__type__":"cc.Size","width":750,"height":1350},"_trs":{"__type__":"TypedArray","ctor":"Float64Array","array":[0,0,0,0,0,0,1,1,1,1]}},{"__type__":"cc.Node","_name":"New Layout","_parent":{"__id__":2},"_children":[{"__id__":6},{"__id__":10},{"__id__":14},{"__id__":18},{"__id__":22},{"__id__":26}],"_components":[{"__type__":"cc.Sprite","node":{"__id__":5},"_materials":[{"__uuid__":"ecpdLyjvZBwrvm+cedCcQy"}],"_type":1,"_sizeMode":0},{"__type__":"cc.Layout","node":{"__id__":5},"_layoutSize":{"__type__":"cc.Size","width":400,"height":800},"_N$layoutType":3,"_N$spacingX":100,"_N$spacingY":100}],"_contentSize":{"__type__":"cc.Size","width":400,"height":800},"_trs":{"__type__":"TypedArray","ctor":"Float64Array","array":[0,0,0,0,0,0,1,1,1,1]}},{"__type__":"cc.Node","_name":"jieju_1","_parent":{"__id__":5},"_children":[{"__id__":7}],"_components":[{"__id__":9}],"_contentSize":{"__type__":"cc.Size","width":150,"height":200},"_trs":{"__type__":"TypedArray","ctor":"Float64Array","array":[-125,300,0,0,0,0,1,1,1,1]}},{"__type__":"cc.Node","_name":"Background","_parent":{"__id__":6},"_components":[{"__id__":8},{"__type__":"cc.Widget","node":{"__id__":7},"alignMode":0,"_alignFlags":45,"_originalWidth":100,"_originalHeight":40}],"_color":{"__type__":"cc.Color","r":230,"g":230,"b":230},"_contentSize":{"__type__":"cc.Size","width":150,"height":200},"_trs":{"__type__":"TypedArray","ctor":"Float64Array","array":[0,0,0,0,0,0,1,1,1,1]}},{"__type__":"cc.Sprite","node":{"__id__":7},"_materials":[{"__uuid__":"ecpdLyjvZBwrvm+cedCcQy"}],"_spriteFrame":{"__uuid__":"f0BIwQ8D5Ml7nTNQbh1YlS"},"_type":1,"_sizeMode":0},{"__type__":"cc.Button","node":{"__id__":6},"_normalMaterial":{"__uuid__":"ecpdLyjvZBwrvm+cedCcQy"},"_N$transition":1,"transition":1,"_N$normalColor":{"__type__":"cc.Color","r":230,"g":230,"b":230},"_N$pressedColor":{"__type__":"cc.Color","r":200,"g":200,"b":200},"pressedColor":{"__type__":"cc.Color","r":200,"g":200,"b":200},"_N$disabledColor":{"__type__":"cc.Color","r":120,"g":120,"b":120,"a":200},"_N$pressedSprite":{"__uuid__":"e97GVMl6JHh5Ml5qEDdSGa"},"pressedSprite":{"__uuid__":"e97GVMl6JHh5Ml5qEDdSGa"},"_N$hoverSprite":{"__uuid__":"f0BIwQ8D5Ml7nTNQbh1YlS"},"hoverSprite":{"__uuid__":"f0BIwQ8D5Ml7nTNQbh1YlS"},"_N$disabledSprite":{"__uuid__":"29FYIk+N1GYaeWH/q1NxQO"},"_N$target":{"__id__":7}},{"__type__":"cc.Node","_name":"jieju_2","_parent":{"__id__":5},"_children":[{"__id__":11}],"_components":[{"__id__":13}],"_contentSize":{"__type__":"cc.Size","width":150,"height":200},"_trs":{"__type__":"TypedArray","ctor":"Float64Array","array":[125,300,0,0,0,0,1,1,1,1]}},{"__type__":"cc.Node","_name":"Background","_parent":{"__id__":10},"_components":[{"__id__":12},{"__type__":"cc.Widget","node":{"__id__":11},"alignMode":0,"_alignFlags":45,"_originalWidth":100,"_originalHeight":40}],"_color":{"__type__":"cc.Color","r":230,"g":230,"b":230},"_contentSize":{"__type__":"cc.Size","width":150,"height":200},"_trs":{"__type__":"TypedArray","ctor":"Float64Array","array":[0,0,0,0,0,0,1,1,1,1]}},{"__type__":"cc.Sprite","node":{"__id__":11},"_materials":[{"__uuid__":"ecpdLyjvZBwrvm+cedCcQy"}],"_spriteFrame":{"__uuid__":"f0BIwQ8D5Ml7nTNQbh1YlS"},"_type":1,"_sizeMode":0},{"__type__":"cc.Button","node":{"__id__":10},"_normalMaterial":{"__uuid__":"ecpdLyjvZBwrvm+cedCcQy"},"_N$transition":1,"transition":1,"_N$normalColor":{"__type__":"cc.Color","r":230,"g":230,"b":230},"_N$pressedColor":{"__type__":"cc.Color","r":200,"g":200,"b":200},"pressedColor":{"__type__":"cc.Color","r":200,"g":200,"b":200},"_N$disabledColor":{"__type__":"cc.Color","r":120,"g":120,"b":120,"a":200},"_N$pressedSprite":{"__uuid__":"e97GVMl6JHh5Ml5qEDdSGa"},"pressedSprite":{"__uuid__":"e97GVMl6JHh5Ml5qEDdSGa"},"_N$hoverSprite":{"__uuid__":"f0BIwQ8D5Ml7nTNQbh1YlS"},"hoverSprite":{"__uuid__":"f0BIwQ8D5Ml7nTNQbh1YlS"},"_N$disabledSprite":{"__uuid__":"29FYIk+N1GYaeWH/q1NxQO"},"_N$target":{"__id__":11}},{"__type__":"cc.Node","_name":"jieju_3","_parent":{"__id__":5},"_children":[{"__id__":15}],"_components":[{"__id__":17}],"_contentSize":{"__type__":"cc.Size","width":150,"height":200},"_trs":{"__type__":"TypedArray","ctor":"Float64Array","array":[-125,0,0,0,0,0,1,1,1,1]}},{"__type__":"cc.Node","_name":"Background","_parent":{"__id__":14},"_components":[{"__id__":16},{"__type__":"cc.Widget","node":{"__id__":15},"alignMode":0,"_alignFlags":45,"_originalWidth":100,"_originalHeight":40}],"_color":{"__type__":"cc.Color","r":230,"g":230,"b":230},"_contentSize":{"__type__":"cc.Size","width":150,"height":200},"_trs":{"__type__":"TypedArray","ctor":"Float64Array","array":[0,0,0,0,0,0,1,1,1,1]}},{"__type__":"cc.Sprite","node":{"__id__":15},"_materials":[{"__uuid__":"ecpdLyjvZBwrvm+cedCcQy"}],"_spriteFrame":{"__uuid__":"f0BIwQ8D5Ml7nTNQbh1YlS"},"_type":1,"_sizeMode":0},{"__type__":"cc.Button","node":{"__id__":14},"_normalMaterial":{"__uuid__":"ecpdLyjvZBwrvm+cedCcQy"},"_N$transition":1,"transition":1,"_N$normalColor":{"__type__":"cc.Color","r":230,"g":230,"b":230},"_N$pressedColor":{"__type__":"cc.Color","r":200,"g":200,"b":200},"pressedColor":{"__type__":"cc.Color","r":200,"g":200,"b":200},"_N$disabledColor":{"__type__":"cc.Color","r":120,"g":120,"b":120,"a":200},"_N$pressedSprite":{"__uuid__":"e97GVMl6JHh5Ml5qEDdSGa"},"pressedSprite":{"__uuid__":"e97GVMl6JHh5Ml5qEDdSGa"},"_N$hoverSprite":{"__uuid__":"f0BIwQ8D5Ml7nTNQbh1YlS"},"hoverSprite":{"__uuid__":"f0BIwQ8D5Ml7nTNQbh1YlS"},"_N$disabledSprite":{"__uuid__":"29FYIk+N1GYaeWH/q1NxQO"},"_N$target":{"__id__":15}},{"__type__":"cc.Node","_name":"jieju_4","_parent":{"__id__":5},"_children":[{"__id__":19}],"_components":[{"__id__":21}],"_contentSize":{"__type__":"cc.Size","width":150,"height":200},"_trs":{"__type__":"TypedArray","ctor":"Float64Array","array":[125,0,0,0,0,0,1,1,1,1]}},{"__type__":"cc.Node","_name":"Background","_parent":{"__id__":18},"_components":[{"__id__":20},{"__type__":"cc.Widget","node":{"__id__":19},"alignMode":0,"_alignFlags":45,"_originalWidth":100,"_originalHeight":40}],"_color":{"__type__":"cc.Color","r":230,"g":230,"b":230},"_contentSize":{"__type__":"cc.Size","width":150,"height":200},"_trs":{"__type__":"TypedArray","ctor":"Float64Array","array":[0,0,0,0,0,0,1,1,1,1]}},{"__type__":"cc.Sprite","node":{"__id__":19},"_materials":[{"__uuid__":"ecpdLyjvZBwrvm+cedCcQy"}],"_spriteFrame":{"__uuid__":"f0BIwQ8D5Ml7nTNQbh1YlS"},"_type":1,"_sizeMode":0},{"__type__":"cc.Button","node":{"__id__":18},"_normalMaterial":{"__uuid__":"ecpdLyjvZBwrvm+cedCcQy"},"_N$transition":1,"transition":1,"_N$normalColor":{"__type__":"cc.Color","r":230,"g":230,"b":230},"_N$pressedColor":{"__type__":"cc.Color","r":200,"g":200,"b":200},"pressedColor":{"__type__":"cc.Color","r":200,"g":200,"b":200},"_N$disabledColor":{"__type__":"cc.Color","r":120,"g":120,"b":120,"a":200},"_N$pressedSprite":{"__uuid__":"e97GVMl6JHh5Ml5qEDdSGa"},"pressedSprite":{"__uuid__":"e97GVMl6JHh5Ml5qEDdSGa"},"_N$hoverSprite":{"__uuid__":"f0BIwQ8D5Ml7nTNQbh1YlS"},"hoverSprite":{"__uuid__":"f0BIwQ8D5Ml7nTNQbh1YlS"},"_N$disabledSprite":{"__uuid__":"29FYIk+N1GYaeWH/q1NxQO"},"_N$target":{"__id__":19}},{"__type__":"cc.Node","_name":"jieju_5","_parent":{"__id__":5},"_children":[{"__id__":23}],"_components":[{"__id__":25}],"_contentSize":{"__type__":"cc.Size","width":150,"height":200},"_trs":{"__type__":"TypedArray","ctor":"Float64Array","array":[-125,-300,0,0,0,0,1,1,1,1]}},{"__type__":"cc.Node","_name":"Background","_parent":{"__id__":22},"_components":[{"__id__":24},{"__type__":"cc.Widget","node":{"__id__":23},"alignMode":0,"_alignFlags":45,"_originalWidth":100,"_originalHeight":40}],"_color":{"__type__":"cc.Color","r":230,"g":230,"b":230},"_contentSize":{"__type__":"cc.Size","width":150,"height":200},"_trs":{"__type__":"TypedArray","ctor":"Float64Array","array":[0,0,0,0,0,0,1,1,1,1]}},{"__type__":"cc.Sprite","node":{"__id__":23},"_materials":[{"__uuid__":"ecpdLyjvZBwrvm+cedCcQy"}],"_spriteFrame":{"__uuid__":"f0BIwQ8D5Ml7nTNQbh1YlS"},"_type":1,"_sizeMode":0},{"__type__":"cc.Button","node":{"__id__":22},"_normalMaterial":{"__uuid__":"ecpdLyjvZBwrvm+cedCcQy"},"_N$transition":1,"transition":1,"_N$normalColor":{"__type__":"cc.Color","r":230,"g":230,"b":230},"_N$pressedColor":{"__type__":"cc.Color","r":200,"g":200,"b":200},"pressedColor":{"__type__":"cc.Color","r":200,"g":200,"b":200},"_N$disabledColor":{"__type__":"cc.Color","r":120,"g":120,"b":120,"a":200},"_N$pressedSprite":{"__uuid__":"e97GVMl6JHh5Ml5qEDdSGa"},"pressedSprite":{"__uuid__":"e97GVMl6JHh5Ml5qEDdSGa"},"_N$hoverSprite":{"__uuid__":"f0BIwQ8D5Ml7nTNQbh1YlS"},"hoverSprite":{"__uuid__":"f0BIwQ8D5Ml7nTNQbh1YlS"},"_N$disabledSprite":{"__uuid__":"29FYIk+N1GYaeWH/q1NxQO"},"_N$target":{"__id__":23}},{"__type__":"cc.Node","_name":"jieju_6","_parent":{"__id__":5},"_children":[{"__id__":27}],"_components":[{"__id__":29}],"_contentSize":{"__type__":"cc.Size","width":150,"height":200},"_trs":{"__type__":"TypedArray","ctor":"Float64Array","array":[125,-300,0,0,0,0,1,1,1,1]}},{"__type__":"cc.Node","_name":"Background","_parent":{"__id__":26},"_components":[{"__id__":28},{"__type__":"cc.Widget","node":{"__id__":27},"alignMode":0,"_alignFlags":45,"_originalWidth":100,"_originalHeight":40}],"_color":{"__type__":"cc.Color","r":230,"g":230,"b":230},"_contentSize":{"__type__":"cc.Size","width":150,"height":200},"_trs":{"__type__":"TypedArray","ctor":"Float64Array","array":[0,0,0,0,0,0,1,1,1,1]}},{"__type__":"cc.Sprite","node":{"__id__":27},"_materials":[{"__uuid__":"ecpdLyjvZBwrvm+cedCcQy"}],"_spriteFrame":{"__uuid__":"f0BIwQ8D5Ml7nTNQbh1YlS"},"_type":1,"_sizeMode":0},{"__type__":"cc.Button","node":{"__id__":26},"_normalMaterial":{"__uuid__":"ecpdLyjvZBwrvm+cedCcQy"},"_N$transition":1,"transition":1,"_N$normalColor":{"__type__":"cc.Color","r":230,"g":230,"b":230},"_N$pressedColor":{"__type__":"cc.Color","r":200,"g":200,"b":200},"pressedColor":{"__type__":"cc.Color","r":200,"g":200,"b":200},"_N$disabledColor":{"__type__":"cc.Color","r":120,"g":120,"b":120,"a":200},"_N$pressedSprite":{"__uuid__":"e97GVMl6JHh5Ml5qEDdSGa"},"pressedSprite":{"__uuid__":"e97GVMl6JHh5Ml5qEDdSGa"},"_N$hoverSprite":{"__uuid__":"f0BIwQ8D5Ml7nTNQbh1YlS"},"hoverSprite":{"__uuid__":"f0BIwQ8D5Ml7nTNQbh1YlS"},"_N$disabledSprite":{"__uuid__":"29FYIk+N1GYaeWH/q1NxQO"},"_N$target":{"__id__":27}},{"__type__":"cc.Node","_name":"backtogame","_parent":{"__id__":2},"_children":[{"__id__":31}],"_components":[{"__id__":32}],"_contentSize":{"__type__":"cc.Size","width":120,"height":60},"_trs":{"__type__":"TypedArray","ctor":"Float64Array","array":[-280,600,0,0,0,0,1,1,1,1]}},{"__type__":"cc.Node","_name":"Background","_parent":{"__id__":30},"_components":[{"__type__":"cc.Sprite","node":{"__id__":31},"_materials":[{"__uuid__":"ecpdLyjvZBwrvm+cedCcQy"}],"_spriteFrame":{"__uuid__":"79wIen5AhMFK7r3P38IBEI"},"_type":1,"_sizeMode":0},{"__type__":"cc.Widget","node":{"__id__":31},"alignMode":0,"_alignFlags":45,"_originalWidth":100,"_originalHeight":40}],"_color":{"__type__":"cc.Color","r":230,"g":230,"b":230},"_contentSize":{"__type__":"cc.Size","width":120,"height":60},"_trs":{"__type__":"TypedArray","ctor":"Float64Array","array":[0,0,0,0,0,0,1,1,1,1]}},{"__type__":"cc.Button","node":{"__id__":30},"_normalMaterial":{"__uuid__":"ecpdLyjvZBwrvm+cedCcQy"},"_N$transition":1,"transition":1,"_N$normalColor":{"__type__":"cc.Color","r":230,"g":230,"b":230},"_N$pressedColor":{"__type__":"cc.Color","r":200,"g":200,"b":200},"pressedColor":{"__type__":"cc.Color","r":200,"g":200,"b":200},"_N$disabledColor":{"__type__":"cc.Color","r":120,"g":120,"b":120,"a":200},"_N$pressedSprite":{"__uuid__":"e97GVMl6JHh5Ml5qEDdSGa"},"pressedSprite":{"__uuid__":"e97GVMl6JHh5Ml5qEDdSGa"},"_N$hoverSprite":{"__uuid__":"f0BIwQ8D5Ml7nTNQbh1YlS"},"hoverSprite":{"__uuid__":"f0BIwQ8D5Ml7nTNQbh1YlS"},"_N$disabledSprite":{"__uuid__":"29FYIk+N1GYaeWH/q1NxQO"},"_N$target":{"__id__":31}}]]